orun/__init__.py
orun/commands.py
orun/consensus.py
orun/consensus_config.py
orun/core.py
orun/db.py
orun/main.py
orun/models_config.py
orun/profiles_manager.py
orun/prompts_manager.py
orun/rich_utils.py
orun/search_config.py
orun/tools.py
orun/tui.py
orun/utils.py
orun/yolo.py
orun/data/consensus/best_of_three.json
orun/data/consensus/code_review.json
orun/data/consensus/iterative_improve.json
orun/data/consensus/multi_expert.json
orun/data/consensus/research_paper.json
orun/data/consensus/vision_code.json
orun/data/consensus/vision_consensus.json
orun/data/profiles/analyst.json
orun/data/profiles/coder.json
orun/data/profiles/concise.json
orun/data/profiles/reviewer.json
orun/data/profiles/system.json
orun/data/profiles/tutor.json
orun/data/profiles/writer.json
orun/data/prompts/agility_story.md
orun/data/prompts/ai.md
orun/data/prompts/analyst.md
orun/data/prompts/analyze_answers.md
orun/data/prompts/analyze_bill.md
orun/data/prompts/analyze_bill_short.md
orun/data/prompts/analyze_candidates.md
orun/data/prompts/analyze_cfp_submission.md
orun/data/prompts/analyze_claims.md
orun/data/prompts/analyze_comments.md
orun/data/prompts/analyze_debate.md
orun/data/prompts/analyze_email_headers.md
orun/data/prompts/analyze_incident.md
orun/data/prompts/analyze_interviewer_techniques.md
orun/data/prompts/analyze_logs.md
orun/data/prompts/analyze_malware.md
orun/data/prompts/analyze_military_strategy.md
orun/data/prompts/analyze_mistakes.md
orun/data/prompts/analyze_paper.md
orun/data/prompts/analyze_paper_simple.md
orun/data/prompts/analyze_patent.md
orun/data/prompts/analyze_personality.md
orun/data/prompts/analyze_presentation.md
orun/data/prompts/analyze_product_feedback.md
orun/data/prompts/analyze_proposition.md
orun/data/prompts/analyze_prose.md
orun/data/prompts/analyze_prose_json.md
orun/data/prompts/analyze_prose_pinker.md
orun/data/prompts/analyze_risk.md
orun/data/prompts/analyze_sales_call.md
orun/data/prompts/analyze_spiritual_text.md
orun_py-1.4.0.dist-info/METADATA
orun_py-1.4.0.dist-info/WHEEL
orun_py-1.4.0.dist-info/entry_points.txt
orun_py-1.4.0.dist-info/RECORD
