Metadata-Version: 2.4
Name: orun-py
Version: 1.4.0
Summary: Add your description here
Project-URL: Homepage, https://github.com/CBoYXD/orun
Project-URL: Repository, https://github.com/CBoYXD/orun
Project-URL: Issues, https://github.com/CBoYXD/orun/issues
Project-URL: Documentation, https://github.com/CBoYXD/orun/blob/main/README.md
Requires-Python: >=3.10
Requires-Dist: arxiv>=2.3.1
Requires-Dist: ddgs>=9.10.0
Requires-Dist: langdetect>=1.0.9
Requires-Dist: ollama>=0.6.1
Requires-Dist: peewee>=3.18
Requires-Dist: pillow>=12.0.0
Requires-Dist: rich>=14.2.0
Requires-Dist: textual>=0.70.0
